wildcard_core/__init__.py
wildcard_core/auth/__init__.py
wildcard_core/auth/auth_helper.py
wildcard_core/auth/auth_status.py
wildcard_core/auth/auth_types.py
wildcard_core/auth/oauth_helper.py
wildcard_core/client/WildcardBaseClient.py
wildcard_core/client/__init__.py
wildcard_core/client/config.yml
wildcard_core/client/responseProcessing/IResponseProcessor.py
wildcard_core/client/responseProcessing/__init__.py
wildcard_core/client/responseProcessing/services/AirtableResponseProcessor.py
wildcard_core/client/responseProcessing/services/BraveSearchResponseProcessor.py
wildcard_core/client/responseProcessing/services/GmailResponseProcessor.py
wildcard_core/client/responseProcessing/services/ShopifyResponseProcessor.py
wildcard_core/client/responseProcessing/services/__init__.py
wildcard_core/client/responseProcessing/services/test_gmail_response_processor.py
wildcard_core/client/responseProcessing/tests/processed_documents.json
wildcard_core/client/responseProcessing/tests/testLargeThread.json
wildcard_core/client/responseProcessing/tests/test_GmailResponseProcessor.py
wildcard_core/client/tests/README.md
wildcard_core/client/tests/__init__.py
wildcard_core/client/tests/shared.py
wildcard_core/client/tests/testParseOpenApi.py
wildcard_core/client/tests/testParseOpenApiById.py
wildcard_core/client/tests/testParseOpenApiMerge.py
wildcard_core/client/tests/testRunToolSearchClient.py
wildcard_core/client/types.py
wildcard_core/client/utils/__init__.py
wildcard_core/client/utils/handle_merge_openapi.py
wildcard_core/client/utils/helpers.py
wildcard_core/client/utils/parse_openapi.py
wildcard_core/events/__init__.py
wildcard_core/events/types.py
wildcard_core/logging/types.py
wildcard_core/models/Action.py
wildcard_core/models/IdRegistry.py
wildcard_core/models/__init__.py
wildcard_core/models/api_service.py
wildcard_core/tool_registry/RegistryDirectory.py
wildcard_core/tool_registry/__init__.py
wildcard_core/tool_registry/tools/DuckDuckGo/DuckDuckGoTool.py
wildcard_core-0.1.7.dist-info/METADATA
wildcard_core-0.1.7.dist-info/WHEEL
wildcard_core-0.1.7.dist-info/RECORD
