Metadata-Version: 2.1
Name: wildcard-core
Version: 0.1.7
Summary: Core functionality for the Wildcard ecosystem.
License: Elastic-2.0
Author: Kaushik
Author-email: kaushik@wild-card.ai
Requires-Python: >=3.9,<4.0
Classifier: License :: Other/Proprietary License
Classifier: Programming Language :: Python :: 3
Classifier: Programming Language :: Python :: 3.9
Classifier: Programming Language :: Python :: 3.10
Classifier: Programming Language :: Python :: 3.11
Classifier: Programming Language :: Python :: 3.12
Classifier: Programming Language :: Python :: 3.13
Requires-Dist: PyYAML (>=6.0.2)
Requires-Dist: aiohttp (>=3.8.6)
Requires-Dist: asyncio (>=3.4.3)
Requires-Dist: azure-storage-blob (>=12.19.0)
Requires-Dist: docstring_parser (>=0.16)
Requires-Dist: inflection (>=0.5.1)
Requires-Dist: parameterized (>=0.9.0)
Requires-Dist: pydantic (>=2.7.4,<3.0.0)
Requires-Dist: requests (>=2.32.3)
Requires-Dist: tenacity (>=8.1.0,<10.0.0)
Requires-Dist: wildcard-integrations[airtable,gmail] (>=0.1.5)
